vlrdevapi/__init__.py
vlrdevapi/config.py
vlrdevapi/countries.py
vlrdevapi/exceptions.py
vlrdevapi/fetcher.py
vlrdevapi/status.py
vlrdevapi/utils.py
vlrdevapi/events/__init__.py
vlrdevapi/events/info.py
vlrdevapi/events/list_events.py
vlrdevapi/events/match_summary.py
vlrdevapi/events/matches.py
vlrdevapi/events/models.py
vlrdevapi/events/stages.py
vlrdevapi/events/standings.py
vlrdevapi/events/teams.py
vlrdevapi/matches/__init__.py
vlrdevapi/matches/_parser.py
vlrdevapi/matches/completed.py
vlrdevapi/matches/live.py
vlrdevapi/matches/models.py
vlrdevapi/matches/upcoming.py
vlrdevapi/players/__init__.py
vlrdevapi/players/_parser.py
vlrdevapi/players/agent_stats.py
vlrdevapi/players/matches.py
vlrdevapi/players/models.py
vlrdevapi/players/profile.py
vlrdevapi/search/__init__.py
vlrdevapi/search/models.py
vlrdevapi/search/search.py
vlrdevapi/series/__init__.py
vlrdevapi/series/_parser.py
vlrdevapi/series/info.py
vlrdevapi/series/matches.py
vlrdevapi/series/models.py
vlrdevapi/teams/__init__.py
vlrdevapi/teams/info.py
vlrdevapi/teams/matches.py
vlrdevapi/teams/models.py
vlrdevapi/teams/placements.py
vlrdevapi/teams/roster.py
vlrdevapi/teams/transactions.py
vlrdevapi-1.6.0.dist-info/licenses/LICENSE
vlrdevapi-1.6.0.dist-info/METADATA
vlrdevapi-1.6.0.dist-info/WHEEL
vlrdevapi-1.6.0.dist-info/top_level.txt
vlrdevapi-1.6.0.dist-info/RECORD
