Metadata-Version: 2.4
Name: vlrdevapi
Version: 1.6.0
Summary: The comprehensive Python library for VLR.gg Valorant esports data scraping - tournaments, matches, players, and statistics
Author: Vansh
License: MIT License
Project-URL: Homepage, https://github.com/vanshbordia/vlrdevapi
Project-URL: Documentation, https://vlrdevapi.readthedocs.io/en/latest/
Project-URL: Source, https://github.com/vanshbordia/vlrdevapi
Project-URL: Issues, https://github.com/vanshbordia/vlrdevapi/issues
Keywords: valorant,esports,vlr,vlr.gg,scraper,api,gaming,competitive,tournament,statistics,data,vct,web-scraping
Classifier: Development Status :: 5 - Production/Stable
Classifier: Intended Audience :: Developers
Classifier: License :: OSI Approved :: MIT License
Classifier: Programming Language :: Python
Classifier: Programming Language :: Python :: 3
Classifier: Programming Language :: Python :: 3.11
Classifier: Programming Language :: Python :: 3.12
Classifier: Programming Language :: Python :: 3.13
Classifier: Programming Language :: Python :: 3.14
Classifier: Topic :: Internet :: WWW/HTTP
Classifier: Topic :: Software Development :: Libraries :: Python Modules
Requires-Python: >=3.11
License-File: LICENSE
Requires-Dist: beautifulsoup4>=4.12
Requires-Dist: httpx[brotli,http2]>=0.27
Requires-Dist: lxml>=5.0
Requires-Dist: pytest>=8.4.2
Requires-Dist: python-dateutil>=2.8.0
Provides-Extra: test
Requires-Dist: pytest>=8.0.0; extra == "test"
Provides-Extra: dev
Requires-Dist: pytest>=8.0.0; extra == "dev"
Requires-Dist: ruff>=0.6.0; extra == "dev"
Dynamic: license-file
